web_features-0.1.0.dist-info/licenses/LICENSE
webfeatures/__init__.py
webfeatures/features.py
webfeatures/github.py
webfeatures/py.typed
web_features-0.1.0.dist-info/METADATA
web_features-0.1.0.dist-info/WHEEL
web_features-0.1.0.dist-info/top_level.txt
web_features-0.1.0.dist-info/RECORD
