Metadata-Version: 2.4
Name: web-features
Version: 0.1.0
Summary: Library for working with web-features data
Author-email: James Graham <james@hoppipolla.co.uk>
Requires-Python: >=3.12
License-File: LICENSE
Requires-Dist: httpx[http2]>=0.28.1
Requires-Dist: pydantic>=2.11.3
Provides-Extra: test
Requires-Dist: mypy==1.10.0; extra == "test"
Requires-Dist: ruff==0.4.8; extra == "test"
Requires-Dist: pytest==8.3.4; extra == "test"
Requires-Dist: pytest-ruff==0.3.2; extra == "test"
Dynamic: license-file
